{
  "openapi": "3.0.1",
  "info": {
    "title": "webapi",
    "version": "1.0"
  },
  "paths": {
    "/api/Account/token": {
      "post": {
        "tags": [
          "Account"
        ],
        "requestBody": {
          "content": {
            "application/json": {
              "schema": {
                "$ref": "#/components/schemas/LoginBindingModel"
              }
            },
            "text/json": {
              "schema": {
                "$ref": "#/components/schemas/LoginBindingModel"
              }
            },
            "application/*+json": {
              "schema": {
                "$ref": "#/components/schemas/LoginBindingModel"
              }
            }
          }
        },
        "responses": {
          "200": {
            "description": "Success"
          }
        }
      }
    },
    "/api/Account/user-details": {
      "get": {
        "tags": [
          "Account"
        ],
        "responses": {
          "200": {
            "description": "Success"
          }
        }
      }
    },
    "/api/Account/get-user-dob": {
      "get": {
        "tags": [
          "Account"
        ],
        "responses": {
          "200": {
            "description": "Success"
          }
        }
      }
    },
    "/api/MediaItems/create-media-item": {
      "post": {
        "tags": [
          "MediaItems"
        ],
        "requestBody": {
          "content": {
            "application/json": {
              "schema": {
                "$ref": "#/components/schemas/MediaItem"
              }
            },
            "text/json": {
              "schema": {
                "$ref": "#/components/schemas/MediaItem"
              }
            },
            "application/*+json": {
              "schema": {
                "$ref": "#/components/schemas/MediaItem"
              }
            }
          }
        },
        "responses": {
          "200": {
            "description": "Success"
          }
        }
      }
    },
    "/api/MediaItems/add-media-item-thumbnail": {
      "post": {
        "tags": [
          "MediaItems"
        ],
        "requestBody": {
          "content": {
            "application/json": {
              "schema": {
                "$ref": "#/components/schemas/Thumbnail"
              }
            },
            "text/json": {
              "schema": {
                "$ref": "#/components/schemas/Thumbnail"
              }
            },
            "application/*+json": {
              "schema": {
                "$ref": "#/components/schemas/Thumbnail"
              }
            }
          }
        },
        "responses": {
          "200": {
            "description": "Success"
          }
        }
      }
    },
    "/api/MediaItems/get-media-items": {
      "get": {
        "tags": [
          "MediaItems"
        ],
        "parameters": [
          {
            "name": "id",
            "in": "query",
            "schema": {
              "type": "string"
            }
          }
        ],
        "responses": {
          "200": {
            "description": "Success"
          }
        }
      }
    },
    "/api/MediaItems/get-media-item-by-id": {
      "get": {
        "tags": [
          "MediaItems"
        ],
        "parameters": [
          {
            "name": "Id",
            "in": "query",
            "schema": {
              "type": "string"
            }
          }
        ],
        "responses": {
          "200": {
            "description": "Success"
          }
        }
      }
    },
    "/api/MediaItems/patch-media-item": {
      "patch": {
        "tags": [
          "MediaItems"
        ],
        "requestBody": {
          "content": {
            "application/json": {
              "schema": {
                "$ref": "#/components/schemas/MediaItem"
              }
            },
            "text/json": {
              "schema": {
                "$ref": "#/components/schemas/MediaItem"
              }
            },
            "application/*+json": {
              "schema": {
                "$ref": "#/components/schemas/MediaItem"
              }
            }
          }
        },
        "responses": {
          "200": {
            "description": "Success"
          }
        }
      }
    },
    "/api/MediaItems/delete-media-item": {
      "delete": {
        "tags": [
          "MediaItems"
        ],
        "parameters": [
          {
            "name": "id",
            "in": "query",
            "schema": {
              "type": "string"
            }
          }
        ],
        "responses": {
          "200": {
            "description": "Success"
          }
        }
      }
    },
    "/api/UploadEncodeAndStreamFiles/upload-file": {
      "post": {
        "tags": [
          "UploadEncodeAndStreamFiles"
        ],
        "responses": {
          "200": {
            "description": "Success"
          }
        }
      }
    }
  },
  "components": {
    "schemas": {
      "LoginBindingModel": {
        "required": [
          "email",
          "password"
        ],
        "type": "object",
        "properties": {
          "email": {
            "type": "string"
          },
          "password": {
            "type": "string",
            "format": "password"
          }
        },
        "additionalProperties": false
      },
      "MediaItem": {
        "type": "object",
        "properties": {
          "id": {
            "type": "string",
            "nullable": true
          },
          "folderId": {
            "type": "string",
            "nullable": true
          },
          "name": {
            "type": "string",
            "nullable": true
          },
          "userId": {
            "type": "string",
            "nullable": true
          },
          "createdAt": {
            "type": "string",
            "format": "date-time"
          },
          "modifiedAt": {
            "type": "string",
            "format": "date-time"
          },
          "size": {
            "type": "string",
            "nullable": true
          },
          "type": {
            "type": "string",
            "nullable": true
          },
          "mediaType": {
            "type": "string",
            "nullable": true
          },
          "description": {
            "type": "string",
            "nullable": true
          },
          "azureUrl": {
            "type": "string",
            "nullable": true
          },
          "thumbnailUrl": {
            "type": "string",
            "nullable": true
          }
        },
        "additionalProperties": false
      },
      "Thumbnail": {
        "type": "object",
        "properties": {
          "videoAzureUrl": {
            "type": "string",
            "nullable": true
          },
          "thumbnailAzureUrl": {
            "type": "string",
            "nullable": true
          }
        },
        "additionalProperties": false
      }
    }
  }
}